fmp/__init__.py
fmp/config_manager.py
fmp/dynamic.py
fmp/fmp_client.py
fmp/logger.py
fmp/session.py
fmp/fmp_websockets/__init__.py
fmp/fmp_websockets/base_websocket_client.py
fmp/fmp_websockets/crypto_websocket.py
fmp/fmp_websockets/forex_websocket.py
fmp/fmp_websockets/stock_websocket.py
fmp_stable_api-0.0.1.dist-info/LICENSE.txt
fmp_stable_api-0.0.1.dist-info/METADATA
fmp_stable_api-0.0.1.dist-info/WHEEL
fmp_stable_api-0.0.1.dist-info/top_level.txt
fmp_stable_api-0.0.1.dist-info/RECORD
