Metadata-Version: 2.2
Name: fmp-stable-api
Version: 0.0.1
Summary: Python client library for the Financial Modeling Prep API
Home-page: https://github.com/Vimal-Seshadri-Raguraman/FMP
Author: Vimal Seshadri Raguraman
Project-URL: GitHub, https://github.com/Vimal-Seshadri-Raguraman/FMP
Classifier: Development Status :: 3 - Alpha
Classifier: Programming Language :: Python :: 3
Classifier: Operating System :: OS Independent
Classifier: Intended Audience :: Developers
Classifier: Intended Audience :: Financial and Insurance Industry
Classifier: Topic :: Office/Business :: Financial
Requires-Python: >=3.6
License-File: LICENSE.txt
Requires-Dist: requests
Requires-Dist: ratelimit
Requires-Dist: websockets
Provides-Extra: dev
Requires-Dist: pytest; extra == "dev"
Requires-Dist: twine; extra == "dev"
Dynamic: author
Dynamic: classifier
Dynamic: description
Dynamic: description-content-type
Dynamic: home-page
Dynamic: project-url
Dynamic: provides-extra
Dynamic: requires-dist
Dynamic: requires-python
Dynamic: summary
